C_librarianthefirstsecondandlast.py
c_librarianthefirstsecondandlast-1.0.3.dist-info/METADATA
c_librarianthefirstsecondandlast-1.0.3.dist-info/WHEEL
c_librarianthefirstsecondandlast-1.0.3.dist-info/RECORD
